src/lab/final-build/EXP_1sep2010_old_20Sep2011/exp9/codes/dffp/dffp.v
`timescale 1ns/1ns
module dffp(q,clk,d);
input d, clk; 
output q;
reg q;

always @ (posedge clk )
begin
q <= d;
end
endmodule

src/lab/final-build/EXP_1sep2010_old_20Sep2011/exp9/codes/dffp/dffp_tb2.v
`include "dffp.v"
`timescale 1ns/1ns
module dffp2_tb;
	wire q;
	reg d,clk;
	dffp dffp(q, clk, d );
	initial
		begin
	 $monitor(q, d, clk);
      #0 d=1'b1;clk=1'b1;
	#5 d=1'b0;clk=1'b0;
	#5 d=1'b0;clk=1'b1;
	#5 d=1'b1;clk=1'b0;
	#5 d=1'b1;clk=1'b1;
	#5 d=1'b1;clk=1'b0;

	#5 d=1'b0;clk=1'b0;
	#5 d=1'b1;clk=1'b1;
	#5 d=1'b0;clk=1'b0;
	#5 d=1'b1;clk=1'b1;
	#5 d=1'b0;clk=1'b0;
	#5 d=1'b0;clk=1'b0;

	#5 d=1'b1;clk=1'b1;
	#5 d=1'b0;clk=1'b0;
	#5 d=1'b1;clk=1'b1;
	#5 d=1'b1;clk=1'b0;
	end
	always @( d or clk)
#1 $display("t=%t",$time," d=%b",d," clk=%b",clk);

initial  begin
    $dumpfile ("dffp2.vcd"); 
    $dumpvars;
end
endmodule

src/lab/final-build/EXP_1sep2010_old_20Sep2011/exp9/codes/dffp/dffp2.vcd
$date
	Sat Jun 25 17:25:13 2011
$end
$version
	Icarus Verilog
$end
$timescale
	1ns
$end
$scope module dffp2_tb $end
$var wire 1 ! q $end
$var reg 1 " clk $end
$var reg 1 # d $end
$scope module dffp $end
$var wire 1 " clk $end
$var wire 1 # d $end
$var reg 1 ! q $end
$upscope $end
$upscope $end
$enddefinitions $end
#0
$dumpvars
1#
1"
1!
$end
#5
0"
0#
#10
0!
1"
#15
0"
1#
#20
1!
1"
#25
0"
#30
0#
#35
1"
1#
#40
0"
0#
#45
1"
1#
#50
0"
0#
#60
1"
1#
#65
0"
0#
#70
1"
1#
