src/lab/final-build/EXP_1sep2010/exp9/codes/dffp/dffp.v
`timescale 1ns/1ns
module dffp(q,clk,d);
input d, clk; 
output q;
reg q;

always @ (posedge clk )
begin
q <= d;
end
endmodule

src/lab/final-build/EXP_1sep2010/exp9/codes/dffp/dffp_tb3.v
`include "dffp.v"
`timescale 1ns/1ns
module dffp3_tb;
	wire q;
	reg d,clk;
	dffp dffp(q, clk, d );
	initial
		begin
	 $monitor(q, d, clk);
      #0 d=1'b1;clk=1'b0;
	#5 d=1'b0;clk=1'b1;
	#5 d=1'b0;clk=1'b1;
	#5 d=1'b1;clk=1'b0;
	#5 d=1'b1;clk=1'b1;
	#5 d=1'b0;clk=1'b0;

	#5 d=1'b0;clk=1'b0;
	#5 d=1'b1;clk=1'b0;
	#5 d=1'b1;clk=1'b1;
	#5 d=1'b0;clk=1'b1;
	#5 d=1'b0;clk=1'b0;
	#5 d=1'b1;clk=1'b0;

	#5 d=1'b1;clk=1'b1;
	#5 d=1'b0;clk=1'b0;
	#5 d=1'b0;clk=1'b1;
	#5 d=1'b1;clk=1'b0;
	end
	always @( d or clk)
#1 $display("t=%t",$time," d=%b",d," clk=%b",clk);

initial  begin
    $dumpfile ("dffp3.vcd"); 
    $dumpvars;
end
endmodule

src/lab/final-build/EXP_1sep2010/exp9/codes/dffp/dffp3.vcd
$date
	Sat Jun 25 17:25:47 2011
$end
$version
	Icarus Verilog
$end
$timescale
	1ns
$end
$scope module dffp3_tb $end
$var wire 1 ! q $end
$var reg 1 " clk $end
$var reg 1 # d $end
$scope module dffp $end
$var wire 1 " clk $end
$var wire 1 # d $end
$var reg 1 ! q $end
$upscope $end
$upscope $end
$enddefinitions $end
#0
$dumpvars
1#
0"
x!
$end
#5
0!
1"
0#
#15
0"
1#
#20
1!
1"
#25
0"
0#
#35
1#
#40
1"
#45
0#
#50
0"
#55
1#
#60
1"
#65
0"
0#
#70
0!
1"
#75
0"
1#
