src/lab/exp9/codes/mux2/mux2.v
`timescale 1ns/1ns
module mux2( clk, In1, In2, Out );

input clk,In1,In2;
output Out;

reg Out;

always @( clk or In2 or In1)
begin
    Out = ( ~clk & In1 ) | (  clk & In2 );
end

endmodule

src/lab/exp9/codes/mux2/mux2_tb2.v
`timescale 1ns/1ns
`include "mux2.v"
module mux2_tb2;
	wire Out;
	reg In1,In2,clk;
	mux2 mux2(clk, In1, In2, Out );
	initial
		begin
	
   #3 In2=1'b0;In1=1'b1; clk=1'b0;
   #5 In2=1'b1;In1=1'b1; clk=1'b1;
   #3 In2=1'b0;In1=1'b1; clk=1'b1;
   #5 In2=1'b0;In1=1'b0; clk=1'b0;

   #3 In2=1'b0;In1=1'b0; clk=1'b0;
   #5 In2=1'b1;In1=1'b0; clk=1'b1;
   #3 In2=1'b1;In1=1'b1; clk=1'b0;
   #5 In2=1'b0;In1=1'b1; clk=1'b1;
  
   #3 In2=1'b0;In1=1'b0; clk=1'b0;
   #5 In2=1'b1;In1=1'b0; clk=1'b0;
   #3 In2=1'b0;In1=1'b1; clk=1'b1;
   #5 In2=1'b1;In1=1'b0; clk=1'b0;
					
		end

always @( clk or In1 or In2)
#1 $display("t=%t",$time," clk=%b",clk," Out=%b",Out," In=%b%b",In2,In1);

initial  begin
    $dumpfile ("mux2_2.vcd"); 
    $dumpvars;
end
endmodule

src/lab/exp9/codes/mux2/mux2_2.vcd
$date
	Sat Jun 25 18:03:51 2011
$end
$version
	Icarus Verilog
$end
$timescale
	1ns
$end
$scope module mux2_tb2 $end
$var wire 1 ! Out $end
$var reg 1 " In1 $end
$var reg 1 # In2 $end
$var reg 1 $ clk $end
$scope module mux2 $end
$var wire 1 " In1 $end
$var wire 1 # In2 $end
$var wire 1 $ clk $end
$var reg 1 ! Out $end
$upscope $end
$upscope $end
$enddefinitions $end
#0
$dumpvars
x$
x#
x"
x!
$end
#3
1!
0$
1"
0#
#8
1$
1#
#11
0!
0#
#16
0$
0"
#24
1!
1$
1#
#27
0$
1"
#32
0!
1$
0#
#35
0$
0"
#40
1#
#43
1$
1"
0#
#48
0$
0"
1#
