src/lab/final-build/EXP_1sep2010/exp9/codes/dffn/dffn.v
`timescale 1ns/1ns
module dffn(q,clk,d);
input d, clk; 
output q;
reg q;

always @ (negedge clk )
begin
q <= d;
end
endmodule

src/lab/final-build/EXP_1sep2010/exp9/codes/dffn/dffn_tb3.v
`include "dffn.v"
`timescale 1ns/1ns
module dffn3_tb;
	wire q;
	reg d,clk;
	dffn dffn(q, clk, d );
	initial
		begin
	 $monitor(q, d, clk);
      #0 d=1'b1;clk=1'b1;
	#5 d=1'b0;clk=1'b0;
	#5 d=1'b0;clk=1'b1;
	#5 d=1'b0;clk=1'b0;
	#5 d=1'b1;clk=1'b1;
	#5 d=1'b1;clk=1'b0;

	#5 d=1'b1;clk=1'b1;
	#5 d=1'b0;clk=1'b0;
	#5 d=1'b0;clk=1'b1;
	#5 d=1'b0;clk=1'b0;
	#5 d=1'b1;clk=1'b1;

	#5 d=1'b1;clk=1'b0;
	#5 d=1'b1;clk=1'b1;
	#5 d=1'b0;clk=1'b0;
	#5 d=1'b0;clk=1'b1;
	#5 d=1'b0;clk=1'b0;
	end
	always @( d or clk)
#1 $display("t=%t",$time," d=%b",d," clk=%b",clk);

initial  begin
    $dumpfile ("dffn3.vcd"); 
    $dumpvars;
end
endmodule

src/lab/final-build/EXP_1sep2010/exp9/codes/dffn/dffn3.vcd
$date
	Sat Jun 25 17:07:17 2011
$end
$version
	Icarus Verilog
$end
$timescale
	1ns
$end
$scope module dffn3_tb $end
$var wire 1 ! q $end
$var reg 1 " clk $end
$var reg 1 # d $end
$scope module dffn $end
$var wire 1 " clk $end
$var wire 1 # d $end
$var reg 1 ! q $end
$upscope $end
$upscope $end
$enddefinitions $end
#0
$dumpvars
1#
1"
x!
$end
#5
0!
0"
0#
#10
1"
#15
0"
#20
1"
1#
#25
1!
0"
#30
1"
#35
0!
0"
0#
#40
1"
#45
0"
#50
1"
1#
#55
1!
0"
#60
1"
#65
0!
0"
0#
